claudear/__init__.py
claudear/config.py
claudear/main.py
claudear/unified_main.py
claudear/claude/__init__.py
claudear/claude/activity.py
claudear/claude/hooks.py
claudear/claude/runner.py
claudear/core/__init__.py
claudear/core/app.py
claudear/core/config.py
claudear/core/orchestrator.py
claudear/core/state.py
claudear/core/store.py
claudear/core/types.py
claudear/events/__init__.py
claudear/events/types.py
claudear/git/__init__.py
claudear/git/github.py
claudear/git/worktree.py
claudear/linear/__init__.py
claudear/linear/client.py
claudear/linear/labels.py
claudear/linear/models.py
claudear/providers/__init__.py
claudear/providers/base.py
claudear/providers/linear/__init__.py
claudear/providers/linear/provider.py
claudear/providers/linear/webhook.py
claudear/providers/notion/__init__.py
claudear/providers/notion/client.py
claudear/providers/notion/poller.py
claudear/providers/notion/provider.py
claudear/scripts/__init__.py
claudear/scripts/migrate_db.py
claudear/scripts/test_multi_provider.py
claudear/server/__init__.py
claudear/server/app.py
claudear/server/unified_app.py
claudear/server/routes/__init__.py
claudear/server/routes/health.py
claudear/server/routes/unified_webhooks.py
claudear/server/routes/webhooks.py
claudear/tasks/__init__.py
claudear/tasks/manager.py
claudear/tasks/state.py
claudear/tasks/store.py
claudear/utils/__init__.py
claudear-0.2.13.dist-info/METADATA
claudear-0.2.13.dist-info/WHEEL
claudear-0.2.13.dist-info/entry_points.txt
claudear-0.2.13.dist-info/licenses/LICENSE
claudear-0.2.13.dist-info/RECORD
